pyduckdb/__init__.py
pyduckdb/aiopyduckdb/__init__.py
pyduckdb/aiopyduckdb/connection.py
pyduckdb/aiopyduckdb/cursor.py
pyduckdb/aiopyduckdb/utils.py
pyduckdb/core/__init__.py
pyduckdb/core/connection.py
pyduckdb/core/cursor.py
pyduckdb/core/exceptions.py
pyduckdb/core/types.py
pyduckdb/core/utils.py
pyduckdb-0.0.1b3.dist-info/LICENSE
pyduckdb-0.0.1b3.dist-info/METADATA
pyduckdb-0.0.1b3.dist-info/WHEEL
pyduckdb-0.0.1b3.dist-info/top_level.txt
pyduckdb-0.0.1b3.dist-info/RECORD
