Metadata-Version: 2.1
Name: pyduckdb
Version: 0.0.1b3
Summary: A Python wrapper around DuckDB to add some convenience.
Home-page: https://github.com/thesketh/pyduckdb
Author: Travis Hesketh
Author-email: travis@hesketh.scot
License: UNKNOWN
Platform: UNKNOWN
Classifier: Programming Language :: Python :: 3
Classifier: Programming Language :: Python :: 3.7
Classifier: Development Status :: 4 - Beta
Classifier: Natural Language :: English
Classifier: Intended Audience :: Developers
Classifier: Operating System :: OS Independent
Classifier: Topic :: Software Development :: Libraries
Classifier: License :: OSI Approved :: MIT License
Classifier: Typing :: Typed
Requires-Python: >=3.7
Requires-Dist: duckdb (==0.2.5)
Requires-Dist: pep249 (>=0.0.1b3)
